vaxsim/__init__.py
vaxsim/calibration.py
vaxsim/cli.py
vaxsim/model.py
vaxsim/params.yaml
vaxsim/plot.py
vaxsim/utils.py
vaxsim-0.1.3.dist-info/licenses/LICENSE
vaxsim-0.1.3.dist-info/METADATA
vaxsim-0.1.3.dist-info/WHEEL
vaxsim-0.1.3.dist-info/entry_points.txt
vaxsim-0.1.3.dist-info/top_level.txt
vaxsim-0.1.3.dist-info/RECORD
