Metadata-Version: 2.4
Name: vaxsim
Version: 0.1.3
Summary: vaxsim is a python package for simulating the spread of Foot and Mouth Disease (FMD) using a discrete compartmental model (SIRSV framework), along with control interventions such as periodic pulsed vaccination campaigns.
Author-email: Adish Illikkal <adish@artpark.in>
License: MIT
Requires-Python: >=3.11
License-File: LICENSE
Requires-Dist: numpy>=2.2.4
Requires-Dist: pandas>=2.2.3
Requires-Dist: PyYAML>=6.0.1
Requires-Dist: scipy>=1.15.2
Requires-Dist: tqdm>=4.67.1
Provides-Extra: plotting
Requires-Dist: matplotlib>=3.10.1; extra == "plotting"
Requires-Dist: seaborn>=0.13.2; extra == "plotting"
Provides-Extra: dev
Requires-Dist: pytest>=7.4.0; extra == "dev"
Requires-Dist: pytest-cov>=4.1.0; extra == "dev"
Requires-Dist: pytest-mpl>=0.16.1; extra == "dev"
Requires-Dist: pytest-mock>=3.10.0; extra == "dev"
Requires-Dist: build>=1.0.3; extra == "dev"
Requires-Dist: twine>=4.0.2; extra == "dev"
Provides-Extra: docs
Requires-Dist: sphinx>=8.2.3; extra == "docs"
Requires-Dist: sphinx-rtd-theme>=3.0.2; extra == "docs"
Requires-Dist: sphinx-autodoc-typehints>=1.25.2; extra == "docs"
Requires-Dist: myst-parser>=2.0.0; extra == "docs"
Requires-Dist: ipython>=9.0.2; extra == "docs"
Requires-Dist: docutils>=0.20.1; extra == "docs"
Requires-Dist: furo>=2024.1.29; extra == "docs"
Provides-Extra: all
Requires-Dist: vaxsim[dev,docs,plotting]; extra == "all"
Dynamic: license-file
